<annotation>
	<folder>images</folder>
	<filename>281.jpg</filename>
	<path>/home/prasad/Desktop/tf_training/label_image/images/281.jpg</path>
	<source>
		<database>Unknown</database>
	</source>
	<size>
		<width>450</width>
		<height>539</height>
		<depth>3</depth>
	</size>
	<segmented>0</segmented>
	<object>
		<name>knife</name>
		<pose>Unspecified</pose>
		<truncated>0</truncated>
		<difficult>0</difficult>
		<bndbox>
			<xmin>41</xmin>
			<ymin>25</ymin>
			<xmax>433</xmax>
			<ymax>105</ymax>
		</bndbox>
	</object>
	<object>
		<name>knife</name>
		<pose>Unspecified</pose>
		<truncated>0</truncated>
		<difficult>0</difficult>
		<bndbox>
			<xmin>34</xmin>
			<ymin>125</ymin>
			<xmax>436</xmax>
			<ymax>214</ymax>
		</bndbox>
	</object>
	<object>
		<name>knife</name>
		<pose>Unspecified</pose>
		<truncated>0</truncated>
		<difficult>0</difficult>
		<bndbox>
			<xmin>38</xmin>
			<ymin>229</ymin>
			<xmax>433</xmax>
			<ymax>325</ymax>
		</bndbox>
	</object>
	<object>
		<name>knife</name>
		<pose>Unspecified</pose>
		<truncated>0</truncated>
		<difficult>0</difficult>
		<bndbox>
			<xmin>34</xmin>
			<ymin>337</ymin>
			<xmax>427</xmax>
			<ymax>426</ymax>
		</bndbox>
	</object>
	<object>
		<name>knife</name>
		<pose>Unspecified</pose>
		<truncated>0</truncated>
		<difficult>0</difficult>
		<bndbox>
			<xmin>32</xmin>
			<ymin>437</ymin>
			<xmax>425</xmax>
			<ymax>522</ymax>
		</bndbox>
	</object>
</annotation>
